metadata/__init__.py
metadata/main.py
meta_pkg-0.0.1.dist-info/METADATA
meta_pkg-0.0.1.dist-info/WHEEL
meta_pkg-0.0.1.dist-info/entry_points.txt
meta_pkg-0.0.1.dist-info/top_level.txt
meta_pkg-0.0.1.dist-info/RECORD
